amazon_music-1.7.7.dist-info/licenses/LICENSE
amz/__init__.py
amz/api.py
amz/cli.py
amz/converter.py
amz/errors.py
amz/formats.py
amz/gui.py
amz/main.py
amz/metadata.py
amz/printer.py
amz/utils.py
amazon_music-1.7.7.dist-info/METADATA
amazon_music-1.7.7.dist-info/WHEEL
amazon_music-1.7.7.dist-info/entry_points.txt
amazon_music-1.7.7.dist-info/top_level.txt
amazon_music-1.7.7.dist-info/RECORD
