Metadata-Version: 2.4
Name: amazon-music
Version: 1.7.7
Summary: A Python package for interacting with Amazon Music services
Home-page: https://github.com/AmineSoukara/Amazon-Music
Author: Amine Soukara
Author-email: AmineSoukara@gmail.com
Maintainer: Amine Soukara
Maintainer-email: AmineSoukara@gmail.com
License: MIT
Project-URL: Source, https://github.com/AmineSoukara/Amazon-Music
Project-URL: Documentation, https://github.com/AmineSoukara/Amazon-Music#readme
Project-URL: Tracker, https://github.com/AmineSoukara/Amazon-Music/issues
Project-URL: Changelog, https://github.com/AmineSoukara/Amazon-Music/releases
Keywords: amazon,music,cli,api,downloader,streaming,audio
Classifier: Development Status :: 5 - Production/Stable
Classifier: Intended Audience :: Developers
Classifier: Intended Audience :: End Users/Desktop
Classifier: Topic :: Multimedia :: Sound/Audio
Classifier: Topic :: Utilities
Classifier: Natural Language :: English
Classifier: License :: OSI Approved :: MIT License
Classifier: Operating System :: OS Independent
Classifier: Programming Language :: Python :: 3
Classifier: Programming Language :: Python :: 3.8
Classifier: Programming Language :: Python :: 3.9
Classifier: Programming Language :: Python :: 3.10
Classifier: Programming Language :: Python :: 3.11
Classifier: Programming Language :: Python :: 3.12
Classifier: Programming Language :: Python :: Implementation :: CPython
Requires-Python: >=3.8
License-File: LICENSE
Requires-Dist: requests>=2.32.4
Requires-Dist: dotmap>=1.3.30
Requires-Dist: mutagen>=1.47.0
Requires-Dist: pathvalidate>=3.3.1
Requires-Dist: rich>=14.0.0
Requires-Dist: pyfiglet>=1.0.3
Requires-Dist: setuptools>=80.9.0
Provides-Extra: dev
Requires-Dist: pytest>=6.0.0; extra == "dev"
Requires-Dist: pytest-cov>=2.0.0; extra == "dev"
Requires-Dist: mypy>=0.910; extra == "dev"
Requires-Dist: flake8>=3.9.0; extra == "dev"
Requires-Dist: twine>=3.4.0; extra == "dev"
Requires-Dist: wheel>=0.36.0; extra == "dev"
Provides-Extra: gui
Requires-Dist: customtkinter>=5.1.2; extra == "gui"
Dynamic: author
Dynamic: author-email
Dynamic: classifier
Dynamic: description
Dynamic: description-content-type
Dynamic: home-page
Dynamic: keywords
Dynamic: license
Dynamic: license-file
Dynamic: maintainer
Dynamic: maintainer-email
Dynamic: project-url
Dynamic: provides-extra
Dynamic: requires-dist
Dynamic: requires-python
Dynamic: summary
